{
  "Agenda": [
    {
      "id": 1,
      "name": "Elias Braga",
      "email": "eliasjrb@gmail.com",
      "horario": "12:15",
      "atendente": "Mestre na navalha",
      "fotoAtendente": "../assets/magoDaTesoura.png"
    },
    {
      "id": 2,
      "name": "João Atualizado",
      "email": "joaob@gmail.com",
      "horario": "12:45",
      "atendente": "Mestre na navalha",
      "fotoAtendente": "../assets/magoDaTesoura.png"
    },
    {
      "id": 3,
      "name": "Arnaldo",
      "email": "arnaldo@gmail.com",
      "horario": "09:00",
      "atendente": "Mago da tesoura",
      "fotoAtendente": "../assets/mestreNaNavalha.jpg"
    },
    {
      "id": 4,
      "name": "Jorge Luis",
      "email": "jorgel@gmail.com",
      "horario": "16:005",
      "atendente": "Pente de ouro",
      "fotoAtendente": "../assets/penteDeOuro.jpg"
    },
    {
      "id": 5,
      "name": "Jeferson",
      "email": "jeferson@gmail.com",
      "horario": "17:50",
      "atendente": "Pente de ouro",
      "fotoAtendente": "../assets/penteDeOuro.jpg"
    }
  ]
}